Metadata-Version: 2.1
Name: functii-matematice
Version: 1.0.0
Summary: Functii matematice
Author: Nicu B.
